CHANGELOG.md
LICENSE
MANIFEST.in
README.rst
setup.cfg
setup.py
django_cereal/__init__.py
django_cereal/pickle.py
django_cereal.egg-info/PKG-INFO
django_cereal.egg-info/SOURCES.txt
django_cereal.egg-info/dependency_links.txt
django_cereal.egg-info/entry_points.txt
django_cereal.egg-info/not-zip-safe
django_cereal.egg-info/requires.txt
django_cereal.egg-info/top_level.txt
django_cereal/tests/__init__.py
django_cereal/tests/pickle.py
django_cereal/tests/testapp/__init__.py
django_cereal/tests/testapp/models.py
requirements/default.txt
requirements/pkgutils.txt
requirements/test.txt